topsis/__init__.py
topsis/topsis.py
topsis_Aarushi_102216107-1.0.0.dist-info/METADATA
topsis_Aarushi_102216107-1.0.0.dist-info/WHEEL
topsis_Aarushi_102216107-1.0.0.dist-info/entry_points.txt
topsis_Aarushi_102216107-1.0.0.dist-info/top_level.txt
topsis_Aarushi_102216107-1.0.0.dist-info/RECORD
